codext/VERSION.txt
codext/__common__.py
codext/__info__.py
codext/__init__.py
codext/macros.json
codext/base/__init__.py
codext/base/_base.py
codext/base/_base2n.py
codext/base/base100.py
codext/base/base122.py
codext/base/base45.py
codext/base/base85.py
codext/base/base91.py
codext/base/baseN.py
codext/binary/__init__.py
codext/binary/baudot.py
codext/binary/bcd.py
codext/binary/excess3.py
codext/binary/gray.py
codext/binary/manchester.py
codext/binary/rotate.py
codext/common/__init__.py
codext/common/a1z26.py
codext/common/cases.py
codext/common/dummy.py
codext/common/octal.py
codext/common/ordinal.py
codext/compressions/__init__.py
codext/compressions/gzipp.py
codext/compressions/lz77.py
codext/compressions/lz78.py
codext/compressions/pkzip.py
codext/crypto/__init__.py
codext/crypto/affine.py
codext/crypto/atbash.py
codext/crypto/bacon.py
codext/crypto/barbie.py
codext/crypto/citrix.py
codext/crypto/railfence.py
codext/crypto/rot.py
codext/crypto/scytale.py
codext/crypto/shift.py
codext/crypto/xor.py
codext/hashing/__init__.py
codext/hashing/blake.py
codext/hashing/checksums.py
codext/hashing/crypt.py
codext/hashing/md.py
codext/hashing/sha.py
codext/hashing/shake.py
codext/languages/__init__.py
codext/languages/braille.py
codext/languages/galactic.py
codext/languages/ipsum.py
codext/languages/leetspeak.py
codext/languages/morse.py
codext/languages/navajo.py
codext/languages/radio.py
codext/languages/southpark.py
codext/languages/tap.py
codext/languages/tomtom.py
codext/others/__init__.py
codext/others/dna.py
codext/others/kbshift.py
codext/others/letters.py
codext/others/markdown.py
codext/others/uuencode.py
codext/stegano/__init__.py
codext/stegano/hexagram.py
codext/stegano/klopf.py
codext/stegano/resistor.py
codext/stegano/rick.py
codext/stegano/sms.py
codext/stegano/whitespace.py
codext/web/__init__.py
codext/web/html.py
codext/web/url.py
codext-1.15.9.dist-info/licenses/LICENSE
codext-1.15.9.dist-info/METADATA
codext-1.15.9.dist-info/WHEEL
codext-1.15.9.dist-info/entry_points.txt
codext-1.15.9.dist-info/top_level.txt
codext-1.15.9.dist-info/RECORD
