Metadata-Version: 2.4
Name: codext
Version: 1.15.9
Summary: Native codecs extension
Author-email: Alexandre D'Hondt <alexandre.dhondt@gmail.com>
License:                     GNU GENERAL PUBLIC LICENSE
Project-URL: documentation, https://python-codext.readthedocs.io/en/latest/?badge=latest
Project-URL: homepage, https://github.com/dhondta/python-codext
Project-URL: issues, https://github.com/dhondta/python-codext/issues
Project-URL: repository, https://github.com/dhondta/python-codext
Keywords: python,development,programming,codecs,encodings
Classifier: Development Status :: 5 - Production/Stable
Classifier: Environment :: Console
Classifier: Intended Audience :: Developers
Classifier: License :: OSI Approved :: GNU General Public License v3 or later (GPLv3+)
Classifier: Programming Language :: Python :: 3
Classifier: Topic :: Software Development :: Libraries :: Python Modules
Requires-Python: <4,>=3.8
License-File: LICENSE
Requires-Dist: legacycrypt; python_version >= "3.13"
Requires-Dist: markdown2>=2.5.4
Dynamic: license-file
